setup.py
statizy/Binomialdistribution.py
statizy/Gaussiandistribution.py
statizy/Generaldistribution.py
statizy/__init__.py
statizy.egg-info/PKG-INFO
statizy.egg-info/SOURCES.txt
statizy.egg-info/dependency_links.txt
statizy.egg-info/not-zip-safe
statizy.egg-info/top_level.txt