Metadata-Version: 1.0
Name: statizy
Version: 0.1
Summary: Gaussian and Binomial distributions
Home-page: UNKNOWN
Author: Kandarp Patel
Author-email: UNKNOWN
License: UNKNOWN
Platform: UNKNOWN
